Metadata-Version: 2.0
Name: limix
Version: 1.0.12
Summary: A flexible and fast mixed model toolbox.
Home-page: https://github.com/limix/limix
Author: Limix Developers
Author-email: horta@ebi.ac.uk
License: Apache License 2.0
Platform: UNKNOWN
Classifier: Development Status :: 5 - Production/Stable
Classifier: License :: OSI Approved :: MIT License
Classifier: Operating System :: OS Independent
Requires-Dist: asciitree (>=0.3.3)
Requires-Dist: dask[array,bag,dataframe,delayed] (>=0.14)
Requires-Dist: distributed
Requires-Dist: glimix-core (>=1.2.19)
Requires-Dist: h5py
Requires-Dist: joblib (>=0.11)
Requires-Dist: limix-core (>=1.0.1)
Requires-Dist: limix-legacy (>=0.8.12)
Requires-Dist: ncephes (>=1.0.40)
Requires-Dist: numpy-sugar (>=1.0.47)
Requires-Dist: pandas-plink (>=1.2.1)
Requires-Dist: scikit-learn
Requires-Dist: scipy (>=0.19)
Requires-Dist: tqdm (>=4.10)
